{"invoice_info": {"Invoice Date": "09/06/24", "Due Date": "05/06/24", "Invoice No.": "055205954"}, "pages": "2", "month": "November", "account": "O-9589055", "po_number": "PO-0I2U-1292", "invoice_ammounts": {"item_1": {"quantity": "579.10", "rate": "1,750.30", "amount": "1,013,598.73", "type": "Installation", "full_type": "Installation of Cross Connect"}, "item_2": {"quantity": "5,519.81", "rate": "5,201.91", "amount": "28,713,554.84", "type": "Transport", "full_type": "Transport"}, "item_3": {"quantity": "8,360.15", "rate": "930.70", "amount": "7,780,791.61", "type": "Transport", "full_type": "Transport"}, "item_4": {"quantity": "2,983.62", "rate": "504.07", "amount": "1,503,953.33", "type": "Transport", "full_type": "Transport"}, "item_5": {"quantity": "2,999.36", "rate": "6,741.52", "amount": "20,220,245.43", "type": "Transport", "full_type": "Transport"}, "item_6": {"quantity": "98765", "rate": "4,621.34", "amount": "2,414.27", "type": "Transport", "full_type": "Carrier Taxes for Transport"}, "item_7": {"quantity": "7,312.35", "rate": "1,602.87", "amount": "11,720,746.44", "type": "Installation", "full_type": "Installation of Cross Connect"}, "item_8": {"quantity": "8.00", "rate": "-5.00", "amount": "-40.00", "type": "Discount", "full_type": "Special Partnership Discount"}, "item_9": {"quantity": "4,015.41", "rate": "2,505.75", "amount": "10,061,613.61", "type": "Installation", "full_type": "Installation of Cross Connect"}, "item_10": {"quantity": "109.27", "rate": "1,900.69", "amount": "207,688.40", "type": "Installation", "full_type": "Installation of Cross Connect"}, "item_11": {"quantity": "3,183.32", "rate": "1,482.77", "amount": "4,720,131.40", "type": "Transport", "full_type": "Carrier Taxes for Transport"}, "item_12": {"quantity": "4,609.29", "rate": "5,675.02", "amount": "26,157,812.94", "type": "Transport", "full_type": "Transport"}, "item_13": {"quantity": "6,844.22", "rate": "-7,759.38", "amount": "-53,106,903.78", "type": "Installation", "full_type": "Installation of Cross Connect"}, "item_14": {"quantity": "4,076.66", "rate": "4,502.76", "amount": "18,356,221.58", "type": "Installation", "full_type": "Installation of Cross Connect"}, "item_15": {"quantity": "2,316.43", "rate": "4,712.49", "amount": "10,916,153.21", "type": "Installation", "full_type": "Installation of Cross Connect"}, "item_16": {"quantity": "897.13", "rate": "5,924.80", "amount": "5,315,315.82", "type": "Transport", "full_type": "Carrier Taxes for Transport"}, "item_17": {"quantity": "2,070.07", "rate": "425.30", "amount": "880,400.77", "type": "Installation", "full_type": "Installation of Cross Connect"}, "item_18": {"quantity": "2,338.93", "rate": "1,872.81", "amount": "4,380,371.49", "type": "Installation", "full_type": "Installation of Cross Connect"}, "item_19": {"quantity": "1,096.89", "rate": "7,690.01", "amount": "8,435,095.07", "type": "Installation", "full_type": "Installation of Cross Connect"}, "item_20": {"quantity": "762.49", "rate": "4,240.57", "amount": "3,233,392.22", "type": "Installation", "full_type": "Installation of Cross Connect"}, "item_21": {"quantity": "5,424.26", "rate": "3,680.84", "amount": "19,965,833.18", "type": "Transport", "full_type": "Transport"}, "item_22": {"quantity": "1,674.95", "rate": "4,790.42", "amount": "8,023,713.98", "type": "Installation", "full_type": "Installation of Cross Connect"}, "item_23": {"quantity": "3,631.73", "rate": "434.13", "amount": "1,576,642.94", "type": "Installation", "full_type": "Installation of Cross Connect"}, "item_24": {"quantity": "721.30", "rate": "5,897.78", "amount": "4,254,068.71", "type": "Installation", "full_type": "Installation of Cross Connect"}, "item_25": {"quantity": "2,132.74", "rate": "3,625.51", "amount": "7,732,270.20", "type": "Transport", "full_type": "Transport"}, "item_26": {"quantity": "7,705.52", "rate": "8,644.71", "amount": "66,611,985.80", "type": "Transport", "full_type": "Transport"}, "item_27": {"quantity": "2,180.99", "rate": "5,468.87", "amount": "11,927,550.78", "type": "Transport", "full_type": "Transport"}, "item_28": {"quantity": "6,947.59", "rate": "1,289.78", "amount": "8,960,862.63", "type": "Transport", "full_type": "Transport"}, "item_29": {"quantity": "3,117.35", "rate": "7,043.51", "amount": "21,957,085.90", "type": "Transport", "full_type": "Carrier Taxes for Transport"}}, "po_box": "674592", "po_box_address": "Dallas, TX 75267-4592\n", "user_name": "Micro Merchant Systems, Inc.", "user_address": "25 Thomson Place\n4th Floor\n", "value": "$272,677,319.75", "currency": "USD", "place_of_payment": "Switch, Ltd.", "bank_name": "PNC Bank, N.A.", "account_number": "3802512896", "ACH_routing": "083009060", "wire_routing": "043000096", "swift": "PNCCUS33", "deparment_phone": "702.522.2940", "deparment_fax": "702.444.9546", "deparment_email": "accountsreceivable@switch.com", "deparment_website": "www.switch.com"}